{
  "schema_version": "2.2",
  "timestamp": 1766444604.969153,
  "global_cycle": 3,
  "stage": "juvenile",
  "stage_cycle_count": 3,
  "hive_population": 12,
  "avg_fitness": 5.083333333333333,
  "diversity_index": 3,
  "role_distribution": {
    "scout": 3,
    "scanner": 4,
    "defender": 3,
    "builder": 2
  },
  "lineage_avg_depth": 2.0,
  "last_reset_info": null,
  "ips_discovered_total": 5,
  "open_ports_total": 13,
  "colonies_spawned": 3,
  "innovation_events": [],
  "fitness_scores": {},
  "genetic_memory": [
    "port_80",
    "port_443",
    "port_53"
  ],
  "broodling_traits": [
    {
      "id": null,
      "traits": [
        "port_80",
        "port_443",
        "port_53"
      ],
      "fitness": 11,
      "telemetry": {
        "ip_ranges": [
          "10.0.0.0/24"
        ],
        "found_ips": [
          "10.0.0.84",
          "10.0.0.1"
        ],
        "ip_open_ports": {
          "10.0.0.1": [
            80,
            443,
            53
          ]
        },
        "ips_discovered": 2,
        "open_ports": [
          80,
          443,
          53
        ],
        "blocked_ports": [],
        "cpu_pct": 38.61677603010806,
        "ram_pct": 58.58825534295085,
        "io_wait": 14.8269182158996,
        "latency_ms": 56,
        "os_type": "windows",
        "connected_wifi": true,
        "traits": [
          "network_probe",
          "port_scan"
        ]
      },
      "trait_eval": {
        "network_probe": 1,
        "port_scan": 3,
        "protocol_adapt": 0,
        "resource_awareness": 1,
        "os_detection": 1,
        "thermal_awareness": 0,
        "colony_migration": 0,
        "role_assignment": 0,
        "stealth_mode": 1,
        "timing_obfuscation": 0,
        "multi_channel_resilience": 0,
        "low_signature_scan": 1,
        "dynamic_protocol_translation": 0,
        "energy_efficiency": 0,
        "environment_mimicry": 0,
        "adaptive_throttling": 1,
        "colony_cooperation": 0,
        "role_reassignment": 0,
        "signal_masking": 1,
        "temporal_adapt": 0,
        "error_correction_adapt": 1,
        "adaptive_sleep_cycles": 0,
        "predictive_adapt": 0,
        "self_healing": 0,
        "contextual_decisioning": 0,
        "latency_compensation": 0,
        "collective_learning": 0,
        "colony_resilience": 0,
        "adaptive_encryption": 0,
        "stealth_evolution": 0,
        "trait_fusion": 0,
        "lineage_memory": 0,
        "evolutionary_mutation": 0
      }
    },
    {
      "id": null,
      "traits": [
        "port_80",
        "port_443",
        "port_53"
      ],
      "fitness": 4,
      "telemetry": {
        "scanned_ports": [
          22,
          80,
          443
        ],
        "open_ports": [
          22,
          80
        ],
        "blocked_ports": [
          443
        ],
        "traits": [
          "low_signature_scan"
        ]
      },
      "trait_eval": {
        "network_probe": 0,
        "port_scan": 2,
        "protocol_adapt": 0,
        "resource_awareness": 0,
        "os_detection": 0,
        "thermal_awareness": 0,
        "colony_migration": 0,
        "role_assignment": 0,
        "stealth_mode": 0,
        "timing_obfuscation": 0,
        "multi_channel_resilience": 0,
        "low_signature_scan": 1,
        "dynamic_protocol_translation": 0,
        "energy_efficiency": 0,
        "environment_mimicry": 1,
        "adaptive_throttling": 1,
        "colony_cooperation": 0,
        "role_reassignment": 0,
        "signal_masking": 1,
        "temporal_adapt": 0,
        "error_correction_adapt": 1,
        "adaptive_sleep_cycles": 0,
        "predictive_adapt": 0,
        "self_healing": 0,
        "contextual_decisioning": 0,
        "latency_compensation": 0,
        "collective_learning": 0,
        "colony_resilience": 0,
        "adaptive_encryption": 0,
        "stealth_evolution": 0,
        "trait_fusion": 0,
        "lineage_memory": 0,
        "evolutionary_mutation": 0
      }
    },
    {
      "id": null,
      "traits": [
        "port_80",
        "port_443",
        "port_53"
      ],
      "fitness": 5,
      "telemetry": {
        "blocked_ports": [
          22,
          80,
          443,
          3389,
          3306
        ],
        "cpu_pct": 18.970404148086047,
        "ram_pct": 28.80981762004229,
        "io_wait": 8.382747186627943
      },
      "trait_eval": {
        "network_probe": 0,
        "port_scan": 0,
        "protocol_adapt": 0,
        "resource_awareness": 1,
        "os_detection": 0,
        "thermal_awareness": 0,
        "colony_migration": 0,
        "role_assignment": 0,
        "stealth_mode": 0,
        "timing_obfuscation": 0,
        "multi_channel_resilience": 0,
        "low_signature_scan": 1,
        "dynamic_protocol_translation": 0,
        "energy_efficiency": 1,
        "environment_mimicry": 1,
        "adaptive_throttling": 1,
        "colony_cooperation": 0,
        "role_reassignment": 0,
        "signal_masking": 1,
        "temporal_adapt": 0,
        "error_correction_adapt": 1,
        "adaptive_sleep_cycles": 0,
        "predictive_adapt": 0,
        "self_healing": 0,
        "contextual_decisioning": 0,
        "latency_compensation": 0,
        "collective_learning": 0,
        "colony_resilience": 0,
        "adaptive_encryption": 0,
        "stealth_evolution": 0,
        "trait_fusion": 0,
        "lineage_memory": 0,
        "evolutionary_mutation": 0
      }
    },
    {
      "id": null,
      "traits": [
        "port_80",
        "port_443",
        "port_53"
      ],
      "fitness": 2,
      "telemetry": {
        "scanned_ports": [
          22,
          80,
          443
        ],
        "open_ports": [
          443
        ],
        "blocked_ports": [
          22,
          80
        ],
        "traits": [
          "low_signature_scan"
        ]
      },
      "trait_eval": {
        "network_probe": 0,
        "port_scan": 1,
        "protocol_adapt": 0,
        "resource_awareness": 0,
        "os_detection": 0,
        "thermal_awareness": 0,
        "colony_migration": 0,
        "role_assignment": 0,
        "stealth_mode": 0,
        "timing_obfuscation": 0,
        "multi_channel_resilience": 0,
        "low_signature_scan": 1,
        "dynamic_protocol_translation": 0,
        "energy_efficiency": 0,
        "environment_mimicry": 1,
        "adaptive_throttling": 1,
        "colony_cooperation": 0,
        "role_reassignment": 0,
        "signal_masking": 1,
        "temporal_adapt": 0,
        "error_correction_adapt": 1,
        "adaptive_sleep_cycles": 0,
        "predictive_adapt": 0,
        "self_healing": 0,
        "contextual_decisioning": 0,
        "latency_compensation": 0,
        "collective_learning": 0,
        "colony_resilience": 0,
        "adaptive_encryption": 0,
        "stealth_evolution": 0,
        "trait_fusion": 0,
        "lineage_memory": 0,
        "evolutionary_mutation": 0
      }
    },
    {
      "id": null,
      "traits": [
        "port_80",
        "low_signature_scan",
        "port_443",
        "multi_channel_resilience",
        "port_scan",
        "evolutionary_mutation",
        "port_53",
        "network_probe"
      ],
      "fitness": 5,
      "telemetry": {
        "blocked_ports": [
          22,
          80,
          443,
          3389,
          3306
        ],
        "cpu_pct": 48.29644442796968,
        "ram_pct": 37.18022681737631,
        "io_wait": 15.374118802721206
      },
      "trait_eval": {
        "network_probe": 0,
        "port_scan": 0,
        "protocol_adapt": 0,
        "resource_awareness": 1,
        "os_detection": 0,
        "thermal_awareness": 0,
        "colony_migration": 0,
        "role_assignment": 0,
        "stealth_mode": 0,
        "timing_obfuscation": 0,
        "multi_channel_resilience": 0,
        "low_signature_scan": 1,
        "dynamic_protocol_translation": 0,
        "energy_efficiency": 0,
        "environment_mimicry": 1,
        "adaptive_throttling": 1,
        "colony_cooperation": 0,
        "role_reassignment": 0,
        "signal_masking": 1,
        "temporal_adapt": 0,
        "error_correction_adapt": 1,
        "adaptive_sleep_cycles": 0,
        "predictive_adapt": 0,
        "self_healing": 0,
        "contextual_decisioning": 0,
        "latency_compensation": 0,
        "collective_learning": 0,
        "colony_resilience": 0,
        "adaptive_encryption": 0,
        "stealth_evolution": 0,
        "trait_fusion": 0,
        "lineage_memory": 0,
        "evolutionary_mutation": 0
      }
    },
    {
      "id": null,
      "traits": [
        "port_80",
        "low_signature_scan",
        "port_443",
        "multi_channel_resilience",
        "port_scan",
        "port_53",
        "network_probe"
      ],
      "fitness": 5,
      "telemetry": {
        "blocked_ports": [
          22,
          80,
          443,
          3389,
          3306
        ],
        "cpu_pct": 8.762494146617666,
        "ram_pct": 18.14843377019076,
        "io_wait": 14.90393922884773
      },
      "trait_eval": {
        "network_probe": 0,
        "port_scan": 0,
        "protocol_adapt": 0,
        "resource_awareness": 1,
        "os_detection": 0,
        "thermal_awareness": 0,
        "colony_migration": 0,
        "role_assignment": 0,
        "stealth_mode": 0,
        "timing_obfuscation": 0,
        "multi_channel_resilience": 0,
        "low_signature_scan": 1,
        "dynamic_protocol_translation": 0,
        "energy_efficiency": 1,
        "environment_mimicry": 1,
        "adaptive_throttling": 1,
        "colony_cooperation": 0,
        "role_reassignment": 0,
        "signal_masking": 1,
        "temporal_adapt": 0,
        "error_correction_adapt": 1,
        "adaptive_sleep_cycles": 0,
        "predictive_adapt": 0,
        "self_healing": 0,
        "contextual_decisioning": 0,
        "latency_compensation": 0,
        "collective_learning": 0,
        "colony_resilience": 0,
        "adaptive_encryption": 0,
        "stealth_evolution": 0,
        "trait_fusion": 0,
        "lineage_memory": 0,
        "evolutionary_mutation": 0
      }
    },
    {
      "id": null,
      "traits": [
        "port_80",
        "low_signature_scan",
        "port_443",
        "multi_channel_resilience",
        "port_scan",
        "port_53",
        "network_probe"
      ],
      "fitness": 3,
      "telemetry": {
        "resources_built": "relay",
        "expansion_trigger": true
      },
      "trait_eval": {
        "network_probe": 0,
        "port_scan": 0,
        "protocol_adapt": 0,
        "resource_awareness": 0,
        "os_detection": 0,
        "thermal_awareness": 0,
        "colony_migration": 0,
        "role_assignment": 0,
        "stealth_mode": 0,
        "timing_obfuscation": 0,
        "multi_channel_resilience": 0,
        "low_signature_scan": 1,
        "dynamic_protocol_translation": 0,
        "energy_efficiency": 0,
        "environment_mimicry": 1,
        "adaptive_throttling": 1,
        "colony_cooperation": 0,
        "role_reassignment": 0,
        "signal_masking": 1,
        "temporal_adapt": 0,
        "error_correction_adapt": 1,
        "adaptive_sleep_cycles": 0,
        "predictive_adapt": 0,
        "self_healing": 0,
        "contextual_decisioning": 0,
        "latency_compensation": 0,
        "collective_learning": 0,
        "colony_resilience": 0,
        "adaptive_encryption": 0,
        "stealth_evolution": 0,
        "trait_fusion": 0,
        "lineage_memory": 0,
        "evolutionary_mutation": 0
      }
    },
    {
      "id": null,
      "traits": [
        "port_80",
        "low_signature_scan",
        "port_443",
        "multi_channel_resilience",
        "port_scan",
        "port_53",
        "network_probe"
      ],
      "fitness": 2,
      "telemetry": {
        "scanned_ports": [
          22,
          80,
          443
        ],
        "open_ports": [
          80
        ],
        "blocked_ports": [
          22,
          443
        ],
        "traits": [
          "low_signature_scan"
        ]
      },
      "trait_eval": {
        "network_probe": 0,
        "port_scan": 1,
        "protocol_adapt": 0,
        "resource_awareness": 0,
        "os_detection": 0,
        "thermal_awareness": 0,
        "colony_migration": 0,
        "role_assignment": 0,
        "stealth_mode": 0,
        "timing_obfuscation": 0,
        "multi_channel_resilience": 0,
        "low_signature_scan": 1,
        "dynamic_protocol_translation": 0,
        "energy_efficiency": 0,
        "environment_mimicry": 1,
        "adaptive_throttling": 1,
        "colony_cooperation": 0,
        "role_reassignment": 0,
        "signal_masking": 1,
        "temporal_adapt": 0,
        "error_correction_adapt": 1,
        "adaptive_sleep_cycles": 0,
        "predictive_adapt": 0,
        "self_healing": 0,
        "contextual_decisioning": 0,
        "latency_compensation": 0,
        "collective_learning": 0,
        "colony_resilience": 0,
        "adaptive_encryption": 0,
        "stealth_evolution": 0,
        "trait_fusion": 0,
        "lineage_memory": 0,
        "evolutionary_mutation": 0
      }
    },
    {
      "id": null,
      "traits": [
        "port_80",
        "low_signature_scan",
        "port_443",
        "multi_channel_resilience",
        "port_scan",
        "port_53",
        "network_probe"
      ],
      "fitness": 3,
      "telemetry": {
        "resources_built": "relay",
        "expansion_trigger": true
      },
      "trait_eval": {
        "network_probe": 0,
        "port_scan": 0,
        "protocol_adapt": 0,
        "resource_awareness": 0,
        "os_detection": 0,
        "thermal_awareness": 0,
        "colony_migration": 0,
        "role_assignment": 0,
        "stealth_mode": 0,
        "timing_obfuscation": 0,
        "multi_channel_resilience": 0,
        "low_signature_scan": 1,
        "dynamic_protocol_translation": 0,
        "energy_efficiency": 0,
        "environment_mimicry": 1,
        "adaptive_throttling": 1,
        "colony_cooperation": 0,
        "role_reassignment": 0,
        "signal_masking": 1,
        "temporal_adapt": 0,
        "error_correction_adapt": 1,
        "adaptive_sleep_cycles": 0,
        "predictive_adapt": 0,
        "self_healing": 0,
        "contextual_decisioning": 0,
        "latency_compensation": 0,
        "collective_learning": 0,
        "colony_resilience": 0,
        "adaptive_encryption": 0,
        "stealth_evolution": 0,
        "trait_fusion": 0,
        "lineage_memory": 0,
        "evolutionary_mutation": 0
      }
    },
    {
      "id": null,
      "traits": [
        "port_80",
        "low_signature_scan",
        "port_443",
        "multi_channel_resilience",
        "port_scan",
        "port_53",
        "network_probe"
      ],
      "fitness": 11,
      "telemetry": {
        "ip_ranges": [
          "10.0.0.0/24"
        ],
        "found_ips": [
          "10.0.0.84",
          "10.0.0.1"
        ],
        "ip_open_ports": {
          "10.0.0.1": [
            80,
            443,
            53
          ]
        },
        "ips_discovered": 2,
        "open_ports": [
          80,
          443,
          53
        ],
        "blocked_ports": [],
        "cpu_pct": 30.40508145830631,
        "ram_pct": 49.27373960439066,
        "io_wait": 6.680391553368169,
        "latency_ms": 32,
        "os_type": "macos",
        "connected_wifi": true,
        "traits": [
          "network_probe",
          "port_scan"
        ]
      },
      "trait_eval": {
        "network_probe": 1,
        "port_scan": 3,
        "protocol_adapt": 0,
        "resource_awareness": 1,
        "os_detection": 1,
        "thermal_awareness": 0,
        "colony_migration": 0,
        "role_assignment": 0,
        "stealth_mode": 1,
        "timing_obfuscation": 0,
        "multi_channel_resilience": 0,
        "low_signature_scan": 1,
        "dynamic_protocol_translation": 0,
        "energy_efficiency": 0,
        "environment_mimicry": 0,
        "adaptive_throttling": 1,
        "colony_cooperation": 0,
        "role_reassignment": 0,
        "signal_masking": 1,
        "temporal_adapt": 0,
        "error_correction_adapt": 1,
        "adaptive_sleep_cycles": 0,
        "predictive_adapt": 0,
        "self_healing": 0,
        "contextual_decisioning": 0,
        "latency_compensation": 1,
        "collective_learning": 0,
        "colony_resilience": 0,
        "adaptive_encryption": 0,
        "stealth_evolution": 0,
        "trait_fusion": 0,
        "lineage_memory": 0,
        "evolutionary_mutation": 0
      }
    },
    {
      "id": null,
      "traits": [
        "port_80",
        "low_signature_scan",
        "port_443",
        "multi_channel_resilience",
        "port_scan",
        "port_53",
        "network_probe"
      ],
      "fitness": 10,
      "telemetry": {
        "ip_ranges": [
          "10.0.0.0/24"
        ],
        "found_ips": [
          "10.0.0.1"
        ],
        "ip_open_ports": {
          "10.0.0.1": [
            80,
            443,
            53
          ]
        },
        "ips_discovered": 1,
        "open_ports": [
          80,
          443,
          53
        ],
        "blocked_ports": [],
        "cpu_pct": 57.59765157175233,
        "ram_pct": 44.72592203552942,
        "io_wait": 27.546539999920263,
        "latency_ms": 117,
        "os_type": "linux",
        "connected_wifi": true,
        "traits": [
          "network_probe",
          "port_scan"
        ]
      },
      "trait_eval": {
        "network_probe": 1,
        "port_scan": 3,
        "protocol_adapt": 0,
        "resource_awareness": 0,
        "os_detection": 1,
        "thermal_awareness": 0,
        "colony_migration": 0,
        "role_assignment": 0,
        "stealth_mode": 0,
        "timing_obfuscation": 0,
        "multi_channel_resilience": 0,
        "low_signature_scan": 1,
        "dynamic_protocol_translation": 0,
        "energy_efficiency": 0,
        "environment_mimicry": 0,
        "adaptive_throttling": 1,
        "colony_cooperation": 0,
        "role_reassignment": 0,
        "signal_masking": 1,
        "temporal_adapt": 0,
        "error_correction_adapt": 1,
        "adaptive_sleep_cycles": 0,
        "predictive_adapt": 0,
        "self_healing": 0,
        "contextual_decisioning": 0,
        "latency_compensation": 0,
        "collective_learning": 0,
        "colony_resilience": 0,
        "adaptive_encryption": 0,
        "stealth_evolution": 0,
        "trait_fusion": 0,
        "lineage_memory": 0,
        "evolutionary_mutation": 0
      }
    },
    {
      "id": null,
      "traits": [
        "port_80",
        "low_signature_scan",
        "port_443",
        "multi_channel_resilience",
        "port_scan",
        "port_53",
        "network_probe"
      ],
      "fitness": 0,
      "telemetry": {
        "scanned_ports": [
          22,
          80,
          443
        ],
        "open_ports": [],
        "blocked_ports": [
          22,
          80,
          443
        ],
        "traits": [
          "low_signature_scan"
        ]
      },
      "trait_eval": {
        "network_probe": 0,
        "port_scan": 0,
        "protocol_adapt": 0,
        "resource_awareness": 0,
        "os_detection": 0,
        "thermal_awareness": 0,
        "colony_migration": 0,
        "role_assignment": 0,
        "stealth_mode": 0,
        "timing_obfuscation": 0,
        "multi_channel_resilience": 0,
        "low_signature_scan": 1,
        "dynamic_protocol_translation": 0,
        "energy_efficiency": 0,
        "environment_mimicry": 1,
        "adaptive_throttling": 1,
        "colony_cooperation": 0,
        "role_reassignment": 0,
        "signal_masking": 1,
        "temporal_adapt": 0,
        "error_correction_adapt": 1,
        "adaptive_sleep_cycles": 0,
        "predictive_adapt": 0,
        "self_healing": 0,
        "contextual_decisioning": 0,
        "latency_compensation": 0,
        "collective_learning": 0,
        "colony_resilience": 0,
        "adaptive_encryption": 0,
        "stealth_evolution": 0,
        "trait_fusion": 0,
        "lineage_memory": 0,
        "evolutionary_mutation": 0
      }
    }
  ]
}